{
  "title": {
    "zh_cn": "逸兴欢跃",
    "zh_tw": "逸興歡躍",
    "en_us": "Euphoric Ride",
    "ko_kr": "Euphoric Ride",
    "ja_jp": "ワクワクライド",
    "es_es": "Euphoric Ride",
    "fr_fr": "Euphoric Ride",
    "ru_ru": "Euphoric Ride",
    "th_th": "Euphoric Ride",
    "vi_vn": "Euphoric Ride",
    "de_de": "Euphoric Ride",
    "id_id": "Euphoric Ride",
    "pt_pt": "Euphoric Ride",
    "tr_tr": "Euphoric Ride",
    "it_it": "Euphoric Ride"
  },
  "country": {
    "zh_cn": "其他",
    "zh_tw": "其他",
    "en_us": "Others",
    "ko_kr": "기타",
    "ja_jp": "その他",
    "es_es": "Otros",
    "fr_fr": "Autre",
    "ru_ru": "Другое",
    "th_th": "อื่น ๆ",
    "vi_vn": "Khác",
    "de_de": "Anderes",
    "id_id": "Lainnya",
    "pt_pt": "Outros",
    "tr_tr": "Diğer",
    "it_it": "Altro"
  },
  "album": {
    "zh_cn": "珍珠之歌 3",
    "zh_tw": "珍珠之歌 3",
    "en_us": "The Shimmering Voyage Vol. 3",
    "ko_kr": "진주의 노래 3",
    "ja_jp": "真珠の歌 3",
    "es_es": "The Shimmering Voyage Vol. 3",
    "fr_fr": "The Shimmering Voyage Vol. 3",
    "ru_ru": "The Shimmering Voyage Vol. 3",
    "th_th": "The Shimmering Voyage Vol. 3",
    "vi_vn": "The Shimmering Voyage Vol. 3",
    "de_de": "The Shimmering Voyage Vol. 3",
    "id_id": "The Shimmering Voyage Vol. 3",
    "pt_pt": "The Shimmering Voyage Vol. 3",
    "tr_tr": "The Shimmering Voyage Vol. 3",
    "it_it": "The Shimmering Voyage Vol. 3"
  },
  "link_ytmusic": "A1Rk7bQdXPY",
  "duration": 120,
  "bpm": 148,
  "level": 7,
  "score": [],
  "measure": {
    "0": [1, 2]
  },
  "bpm_act": {}
}